README.md
setup.py
instaboostfast/InstaBoost.py
instaboostfast/__init__.py
instaboostfast/affine_transform.py
instaboostfast/config.py
instaboostfast/exceptions.py
instaboostfast/get_instance_group.py
instaboostfast/help_functions.py
instaboostfast/pointByHeatmap.py
instaboostfast/pycococreater.py
instaboostfast/single_image_process.py
instaboostfast.egg-info/PKG-INFO
instaboostfast.egg-info/SOURCES.txt
instaboostfast.egg-info/dependency_links.txt
instaboostfast.egg-info/requires.txt
instaboostfast.egg-info/top_level.txt